README.rst
setup.py
src/zc/__init__.py
src/zc.wsgidriver.egg-info/PKG-INFO
src/zc.wsgidriver.egg-info/SOURCES.txt
src/zc.wsgidriver.egg-info/dependency_links.txt
src/zc.wsgidriver.egg-info/entry_points.txt
src/zc.wsgidriver.egg-info/namespace_packages.txt
src/zc.wsgidriver.egg-info/not-zip-safe
src/zc.wsgidriver.egg-info/requires.txt
src/zc.wsgidriver.egg-info/top_level.txt
src/zc/wsgidriver/__init__.py
src/zc/wsgidriver/example.rst
src/zc/wsgidriver/tests.py