Metadata-Version: 1.0
Name: zc.wsgidriver
Version: 0.1.0
Summary: WSGI+Webdriver for testing Javascript (and optionally WSGI) UIs
Home-page: UNKNOWN
Author: Jim Fulton
Author-email: jim@zope.com
License: ZPL 2.1
Platform: UNKNOWN
